onlyoffice.connector-2.2.0-py3.8-nspkg.pth
onlyoffice/connector/__init__.py
onlyoffice/connector/configure.zcml
onlyoffice/connector/interfaces.py
onlyoffice/connector/permissions.zcml
onlyoffice/connector/setuphandlers.py
onlyoffice/connector/testing.py
onlyoffice/connector/upgrades.py
onlyoffice/connector/upgrades.zcml
onlyoffice/connector/browser/__init__.py
onlyoffice/connector/browser/api.py
onlyoffice/connector/browser/configure.zcml
onlyoffice/connector/browser/controlpanel.py
onlyoffice/connector/browser/menu.py
onlyoffice/connector/browser/app_data/az-Latn-AZ/new.docx
onlyoffice/connector/browser/app_data/az-Latn-AZ/new.docxf
onlyoffice/connector/browser/app_data/az-Latn-AZ/new.pptx
onlyoffice/connector/browser/app_data/az-Latn-AZ/new.xlsx
onlyoffice/connector/browser/app_data/bg-BG/new.docx
onlyoffice/connector/browser/app_data/bg-BG/new.docxf
onlyoffice/connector/browser/app_data/bg-BG/new.pptx
onlyoffice/connector/browser/app_data/bg-BG/new.xlsx
onlyoffice/connector/browser/app_data/cs-CZ/new.docx
onlyoffice/connector/browser/app_data/cs-CZ/new.docxf
onlyoffice/connector/browser/app_data/cs-CZ/new.pptx
onlyoffice/connector/browser/app_data/cs-CZ/new.xlsx
onlyoffice/connector/browser/app_data/de-DE/new.docx
onlyoffice/connector/browser/app_data/de-DE/new.docxf
onlyoffice/connector/browser/app_data/de-DE/new.pptx
onlyoffice/connector/browser/app_data/de-DE/new.xlsx
onlyoffice/connector/browser/app_data/el-GR/new.docx
onlyoffice/connector/browser/app_data/el-GR/new.docxf
onlyoffice/connector/browser/app_data/el-GR/new.pptx
onlyoffice/connector/browser/app_data/el-GR/new.xlsx
onlyoffice/connector/browser/app_data/en-GB/new.docx
onlyoffice/connector/browser/app_data/en-GB/new.docxf
onlyoffice/connector/browser/app_data/en-GB/new.pptx
onlyoffice/connector/browser/app_data/en-GB/new.xlsx
onlyoffice/connector/browser/app_data/en-US/new.docx
onlyoffice/connector/browser/app_data/en-US/new.docxf
onlyoffice/connector/browser/app_data/en-US/new.pptx
onlyoffice.connector-2.2.0.dist-info/AUTHORS.md
onlyoffice.connector-2.2.0.dist-info/LICENSE
onlyoffice.connector-2.2.0.dist-info/METADATA
onlyoffice.connector-2.2.0.dist-info/WHEEL
onlyoffice.connector-2.2.0.dist-info/entry_points.txt
onlyoffice.connector-2.2.0.dist-info/namespace_packages.txt
onlyoffice.connector-2.2.0.dist-info/top_level.txt
onlyoffice.connector-2.2.0.dist-info/RECORD
