Metadata-Version: 2.1
Name: onlyoffice.connector
Version: 2.2.0
Summary: Plone ONLYOFFICE integration plugin (deprecated). Moved to https://pypi.org/project/onlyoffice.plone/
Home-page: https://github.com/ONLYOFFICE/onlyoffice-plone
Author: Ascensio System SIA
Author-email: integration@onlyoffice.com
License: AGPL version 3
Project-URL: PyPI, https://pypi.python.org/pypi/onlyoffice.connector
Project-URL: Source, https://github.com/ONLYOFFICE/onlyoffice-plone
Project-URL: Tracker, https://github.com/ONLYOFFICE/onlyoffice-plone/issues
Keywords: Python Plone
Classifier: Environment :: Web Environment
Classifier: Framework :: Plone
Classifier: Framework :: Plone :: Addon
Classifier: Framework :: Plone :: 5.1
Classifier: Framework :: Plone :: 5.2
Classifier: Programming Language :: Python
Classifier: Programming Language :: Python :: 3.4
Classifier: Programming Language :: Python :: 3.5
Classifier: Programming Language :: Python :: 3.6
Classifier: Programming Language :: Python :: 3.7
Classifier: Operating System :: OS Independent
Classifier: License :: OSI Approved :: GNU Affero General Public License v3
Requires-Python: >=3.4
License-File: LICENSE
License-File: AUTHORS.md
Requires-Dist: setuptools
Requires-Dist: z3c.jbot
Requires-Dist: plone.api (>=1.8.4)
Requires-Dist: plone.restapi
Requires-Dist: plone.app.dexterity
Provides-Extra: test
Requires-Dist: plone.app.testing ; extra == 'test'
Requires-Dist: plone.testing (>=5.0.0) ; extra == 'test'
Requires-Dist: plone.app.contenttypes ; extra == 'test'
Requires-Dist: plone.app.robotframework[debug] ; extra == 'test'
